rsacore.py
rsacore-1.0.1.dist-info/WHEEL
rsacore-1.0.1.dist-info/METADATA
rsacore-1.0.1.dist-info/RECORD
